setup.py
hoyelib/__init__.py
hoyelib/hccmd.py
hoyelib/hclogo.py
hoyelib/hcprint.py
hoyelib.egg-info/PKG-INFO
hoyelib.egg-info/SOURCES.txt
hoyelib.egg-info/dependency_links.txt
hoyelib.egg-info/top_level.txt